setup.py
scripts/sendtx
sendtx/__init__.py
sendtx/halfnode.py
sendtx/halfnode_tools.py
sendtx.egg-info/PKG-INFO
sendtx.egg-info/SOURCES.txt
sendtx.egg-info/dependency_links.txt
sendtx.egg-info/requires.txt
sendtx.egg-info/top_level.txt
sendtx.egg-info/zip-safe