Metadata-Version: 1.0
Name: sendtx
Version: 0.5.1
Summary: Send serialized bitcoin transaction from commandline to bitcoin network
Home-page: https://github.com/slush0/sendtx
Author: slush
Author-email: info@bitcion.cz
License: public domain
Platform: UNKNOWN
